tftk/__init__.py
tftk/activation.py
tftk/augment_ok/image.py
tftk/callback.py
tftk/colab.py
tftk/context.py
tftk/dataset/__init__.py
tftk/dataset/dataset.py
tftk/image/__init__.py
tftk/image/augument.py
tftk/image/dataset/__init__.py
tftk/image/dataset/anomaly_detection.py
tftk/image/dataset/base.py
tftk/image/dataset/classification.py
tftk/image/dataset/utility.py
tftk/image/model/__init__.py
tftk/image/model/autoencoder.py
tftk/image/model/base.py_
tftk/image/model/classification.py
tftk/image/model/dropblock.py
tftk/image/model/efficientnet.py
tftk/image/model/gan.py
tftk/image/model/representation.py
tftk/image/model/resnet.py
tftk/image/model/small_resnet_keras_contrib.py
tftk/image/train.py_
tftk/loss/__init__.py
tftk/loss/loss.py
tftk/mixed_precision.py
tftk/optimizer/__init__.py
tftk/optimizer/optimizer.py
tftk/optimizer/tensorflow_adabound.py
tftk/optuna/__init__.py
tftk/optuna/mongo.py
tftk/optuna/optuna_util.py
tftk/patch/__init__.py
tftk/patch/tensorflow_datasets_issue_35630.py
tftk/patch.py
tftk/resume.py
tftk/rl/__init__.py
tftk/simple_logger.py
tftk/train/__init__.py
tftk/train/contrast.py
tftk/train/image.py
tftk/train/train.py
tftk-0.1.17.dist-info/LICENSE
tftk-0.1.17.dist-info/WHEEL
tftk-0.1.17.dist-info/METADATA
tftk-0.1.17.dist-info/RECORD
